{"z05101":{"c":"BELLOWS FALLS","s":"VT","d":false},"z05141":{"c":"CAMBRIDGEPORT","s":"VT","d":false},"z05142":{"c":"CAVENDISH","s":"VT","d":false},"z05143":{"c":"CHESTER","s":"VT","d":false},"z05144":{"c":"CHESTER DEPOT","s":"VT","d":false},"z05146":{"c":"GRAFTON","s":"VT","d":false},"z05148":{"c":"LONDONDERRY","s":"VT","d":false},"z05149":{"c":"LUDLOW","s":"VT","d":false},"z05150":{"c":"NORTH SPRINGFIELD","s":"VT","d":false},"z05151":{"c":"PERKINSVILLE","s":"VT","d":false},"z05152":{"c":"PERU","s":"VT","d":false},"z05153":{"c":"PROCTORSVILLE","s":"VT","d":false},"z05154":{"c":"SAXTONS RIVER","s":"VT","d":false},"z05155":{"c":"SOUTH LONDONDERRY","s":"VT","d":false},"z05156":{"c":"SPRINGFIELD","s":"VT","d":false},"z05158":{"c":"WESTMINSTER","s":"VT","d":false},"z05159":{"c":"WESTMINSTER STATION","s":"VT","d":false},"z05161":{"c":"WESTON","s":"VT","d":false},"z05100":false,"z05102":false,"z05103":false,"z05104":false,"z05105":false,"z05106":false,"z05107":false,"z05108":false,"z05109":false,"z05110":false,"z05111":false,"z05112":false,"z05113":false,"z05114":false,"z05115":false,"z05116":false,"z05117":false,"z05118":false,"z05119":false,"z05120":false,"z05121":false,"z05122":false,"z05123":false,"z05124":false,"z05125":false,"z05126":false,"z05127":false,"z05128":false,"z05129":false,"z05130":false,"z05131":false,"z05132":false,"z05133":false,"z05134":false,"z05135":false,"z05136":false,"z05137":false,"z05138":false,"z05139":false,"z05140":false,"z05145":false,"z05147":false,"z05157":false,"z05160":false,"z05162":false,"z05163":false,"z05164":false,"z05165":false,"z05166":false,"z05167":false,"z05168":false,"z05169":false,"z05170":false,"z05171":false,"z05172":false,"z05173":false,"z05174":false,"z05175":false,"z05176":false,"z05177":false,"z05178":false,"z05179":false,"z05180":false,"z05181":false,"z05182":false,"z05183":false,"z05184":false,"z05185":false,"z05186":false,"z05187":false,"z05188":false,"z05189":false,"z05190":false,"z05191":false,"z05192":false,"z05193":false,"z05194":false,"z05195":false,"z05196":false,"z05197":false,"z05198":false,"z05199":false}