{"z75630":{"c":"AVINGER","s":"TX","d":false},"z75631":{"c":"BECKVILLE","s":"TX","d":false},"z75633":{"c":"CARTHAGE","s":"TX","d":false},"z75636":{"c":"CASON","s":"TX","d":false},"z75637":{"c":"CLAYTON","s":"TX","d":false},"z75638":{"c":"DAINGERFIELD","s":"TX","d":false},"z75639":{"c":"DE BERRY","s":"TX","d":false},"z75640":{"c":"DIANA","s":"TX","d":false},"z75641":{"c":"EASTON","s":"TX","d":false},"z75642":{"c":"ELYSIAN FIELDS","s":"TX","d":false},"z75643":{"c":"GARY","s":"TX","d":false},"z75644":{"c":"GILMER","s":"TX","d":false},"z75645":{"c":"GILMER","s":"TX","d":false},"z75647":{"c":"GLADEWATER","s":"TX","d":false},"z75650":{"c":"HALLSVILLE","s":"TX","d":false},"z75651":{"c":"HARLETON","s":"TX","d":false},"z75652":{"c":"HENDERSON","s":"TX","d":false},"z75653":{"c":"HENDERSON","s":"TX","d":false},"z75654":{"c":"HENDERSON","s":"TX","d":false},"z75680":{"c":"MINDEN","s":"TX","d":false},"z75656":{"c":"HUGHES SPRINGS","s":"TX","d":false},"z75657":{"c":"JEFFERSON","s":"TX","d":false},"z75658":{"c":"JOINERVILLE","s":"TX","d":false},"z75659":{"c":"JONESVILLE","s":"TX","d":false},"z75660":{"c":"JUDSON","s":"TX","d":false},"z75661":{"c":"KARNACK","s":"TX","d":false},"z75662":{"c":"KILGORE","s":"TX","d":false},"z75663":{"c":"KILGORE","s":"TX","d":false},"z75666":{"c":"LAIRD HILL","s":"TX","d":false},"z75667":{"c":"LANEVILLE","s":"TX","d":false},"z75668":{"c":"LONE STAR","s":"TX","d":false},"z75669":{"c":"LONG BRANCH","s":"TX","d":false},"z75601":{"c":"LONGVIEW","s":"TX","d":false},"z75602":{"c":"LONGVIEW","s":"TX","d":false},"z75603":{"c":"LONGVIEW","s":"TX","d":false},"z75604":{"c":"LONGVIEW","s":"TX","d":false},"z75605":{"c":"LONGVIEW","s":"TX","d":false},"z75606":{"c":"LONGVIEW","s":"TX","d":false},"z75607":{"c":"LONGVIEW","s":"TX","d":false},"z75608":{"c":"LONGVIEW","s":"TX","d":false},"z75615":{"c":"LONGVIEW","s":"TX","d":false},"z75670":{"c":"MARSHALL","s":"TX","d":false},"z75671":{"c":"MARSHALL","s":"TX","d":false},"z75672":{"c":"MARSHALL","s":"TX","d":false},"z75681":{"c":"MOUNT ENTERPRISE","s":"TX","d":false},"z75682":{"c":"NEW LONDON","s":"TX","d":false},"z75683":{"c":"ORE CITY","s":"TX","d":false},"z75684":{"c":"OVERTON","s":"TX","d":false},"z75685":{"c":"PANOLA","s":"TX","d":false},"z75686":{"c":"PITTSBURG","s":"TX","d":false},"z75687":{"c":"PRICE","s":"TX","d":false},"z75688":{"c":"SCOTTSVILLE","s":"TX","d":false},"z75689":{"c":"SELMAN CITY","s":"TX","d":false},"z75691":{"c":"TATUM","s":"TX","d":false},"z75692":{"c":"WASKOM","s":"TX","d":false},"z75693":{"c":"WHITE OAK","s":"TX","d":false},"z75694":{"c":"WOODLAWN","s":"TX","d":false},"z75600":false,"z75609":false,"z75610":false,"z75611":false,"z75612":false,"z75613":false,"z75614":false,"z75616":false,"z75617":false,"z75618":false,"z75619":false,"z75620":false,"z75621":false,"z75622":false,"z75623":false,"z75624":false,"z75625":false,"z75626":false,"z75627":false,"z75628":false,"z75629":false,"z75632":false,"z75634":false,"z75635":false,"z75646":false,"z75648":false,"z75649":false,"z75655":false,"z75664":false,"z75665":false,"z75673":false,"z75674":false,"z75675":false,"z75676":false,"z75677":false,"z75678":false,"z75679":false,"z75690":false,"z75695":false,"z75696":false,"z75697":false,"z75698":false,"z75699":false}