{"z42712":{"c":"BIG CLIFTY","s":"KY","d":false},"z42713":{"c":"BONNIEVILLE","s":"KY","d":false},"z42715":{"c":"BREEDING","s":"KY","d":false},"z42741":{"c":"GLENS FORK","s":"KY","d":false},"z42716":{"c":"BUFFALO","s":"KY","d":false},"z42717":{"c":"BURKESVILLE","s":"KY","d":false},"z42718":{"c":"CAMPBELLSVILLE","s":"KY","d":false},"z42719":{"c":"CAMPBELLSVILLE","s":"KY","d":false},"z42733":{"c":"ELK HORN","s":"KY","d":false},"z42720":{"c":"CANE VALLEY","s":"KY","d":false},"z42721":{"c":"CANEYVILLE","s":"KY","d":false},"z42722":{"c":"CANMER","s":"KY","d":false},"z42724":{"c":"CECILIA","s":"KY","d":false},"z42726":{"c":"CLARKSON","s":"KY","d":false},"z42728":{"c":"COLUMBIA","s":"KY","d":false},"z42753":{"c":"KNIFLEY","s":"KY","d":false},"z42729":{"c":"CUB RUN","s":"KY","d":false},"z42731":{"c":"DUBRE","s":"KY","d":false},"z42732":{"c":"EASTVIEW","s":"KY","d":false},"z42701":{"c":"ELIZABETHTOWN","s":"KY","d":false},"z42702":{"c":"ELIZABETHTOWN","s":"KY","d":false},"z42740":{"c":"GLENDALE","s":"KY","d":false},"z42742":{"c":"GRADYVILLE","s":"KY","d":false},"z42743":{"c":"GREENSBURG","s":"KY","d":false},"z42746":{"c":"HARDYVILLE","s":"KY","d":false},"z42748":{"c":"HODGENVILLE","s":"KY","d":false},"z42749":{"c":"HORSE CAVE","s":"KY","d":false},"z42754":{"c":"LEITCHFIELD","s":"KY","d":false},"z42755":{"c":"LEITCHFIELD","s":"KY","d":false},"z42757":{"c":"MAGNOLIA","s":"KY","d":false},"z42758":{"c":"MANNSVILLE","s":"KY","d":false},"z42759":{"c":"MARROWBONE","s":"KY","d":false},"z42762":{"c":"MILLWOOD","s":"KY","d":false},"z42764":{"c":"MOUNT SHERMAN","s":"KY","d":false},"z42765":{"c":"MUNFORDVILLE","s":"KY","d":false},"z42776":{"c":"SONORA","s":"KY","d":false},"z42782":{"c":"SUMMERSVILLE","s":"KY","d":false},"z42784":{"c":"UPTON","s":"KY","d":false},"z42788":{"c":"WHITE MILLS","s":"KY","d":false},"z42700":false,"z42703":false,"z42704":false,"z42705":false,"z42706":false,"z42707":false,"z42708":false,"z42709":false,"z42710":false,"z42711":false,"z42714":false,"z42723":false,"z42725":false,"z42727":false,"z42730":false,"z42734":false,"z42735":false,"z42736":false,"z42737":false,"z42738":false,"z42739":false,"z42744":false,"z42745":false,"z42747":false,"z42750":false,"z42751":false,"z42752":false,"z42756":false,"z42760":false,"z42761":false,"z42763":false,"z42766":false,"z42767":false,"z42768":false,"z42769":false,"z42770":false,"z42771":false,"z42772":false,"z42773":false,"z42774":false,"z42775":false,"z42777":false,"z42778":false,"z42779":false,"z42780":false,"z42781":false,"z42783":false,"z42785":false,"z42786":false,"z42787":false,"z42789":false,"z42790":false,"z42791":false,"z42792":false,"z42793":false,"z42794":false,"z42795":false,"z42796":false,"z42797":false,"z42798":false,"z42799":false}