{"z16501":{"c":"ERIE","s":"PA","d":false},"z16502":{"c":"ERIE","s":"PA","d":false},"z16503":{"c":"ERIE","s":"PA","d":false},"z16504":{"c":"ERIE","s":"PA","d":false},"z16505":{"c":"ERIE","s":"PA","d":false},"z16506":{"c":"ERIE","s":"PA","d":false},"z16507":{"c":"ERIE","s":"PA","d":false},"z16508":{"c":"ERIE","s":"PA","d":false},"z16509":{"c":"ERIE","s":"PA","d":false},"z16510":{"c":"ERIE","s":"PA","d":false},"z16511":{"c":"ERIE","s":"PA","d":false},"z16512":{"c":"ERIE","s":"PA","d":false},"z16514":{"c":"ERIE","s":"PA","d":false},"z16515":{"c":"ERIE","s":"PA","d":false},"z16522":{"c":"ERIE","s":"PA","d":false},"z16530":{"c":"ERIE","s":"PA","d":false},"z16531":{"c":"ERIE","s":"PA","d":false},"z16534":{"c":"ERIE","s":"PA","d":false},"z16538":{"c":"ERIE","s":"PA","d":false},"z16541":{"c":"ERIE","s":"PA","d":false},"z16544":{"c":"ERIE","s":"PA","d":false},"z16546":{"c":"ERIE","s":"PA","d":false},"z16550":{"c":"ERIE","s":"PA","d":false},"z16553":{"c":"ERIE","s":"PA","d":false},"z16563":{"c":"ERIE","s":"PA","d":false},"z16565":{"c":"ERIE","s":"PA","d":false},"z16532":{"c":"ERIE","s":"PA","d":true},"z16533":{"c":"ERIE","s":"PA","d":true},"z16554":{"c":"ERIE","s":"PA","d":true},"z16500":false,"z16513":false,"z16516":false,"z16517":false,"z16518":false,"z16519":false,"z16520":false,"z16521":false,"z16523":false,"z16524":false,"z16525":false,"z16526":false,"z16527":false,"z16528":false,"z16529":false,"z16535":false,"z16536":false,"z16537":false,"z16539":false,"z16540":false,"z16542":false,"z16543":false,"z16545":false,"z16547":false,"z16548":false,"z16549":false,"z16551":false,"z16552":false,"z16555":false,"z16556":false,"z16557":false,"z16558":false,"z16559":false,"z16560":false,"z16561":false,"z16562":false,"z16564":false,"z16566":false,"z16567":false,"z16568":false,"z16569":false,"z16570":false,"z16571":false,"z16572":false,"z16573":false,"z16574":false,"z16575":false,"z16576":false,"z16577":false,"z16578":false,"z16579":false,"z16580":false,"z16581":false,"z16582":false,"z16583":false,"z16584":false,"z16585":false,"z16586":false,"z16587":false,"z16588":false,"z16589":false,"z16590":false,"z16591":false,"z16592":false,"z16593":false,"z16594":false,"z16595":false,"z16596":false,"z16597":false,"z16598":false,"z16599":false}