{"z07981":{"c":"WHIPPANY","s":"NJ","d":false},"z07999":{"c":"WHIPPANY","s":"NJ","d":false},"z07920":{"c":"BASKING RIDGE","s":"NJ","d":false},"z07939":{"c":"LYONS","s":"NJ","d":false},"z07921":{"c":"BEDMINSTER","s":"NJ","d":false},"z07922":{"c":"BERKELEY HEIGHTS","s":"NJ","d":false},"z07924":{"c":"BERNARDSVILLE","s":"NJ","d":false},"z07926":{"c":"BROOKSIDE","s":"NJ","d":false},"z07927":{"c":"CEDAR KNOLLS","s":"NJ","d":false},"z07928":{"c":"CHATHAM","s":"NJ","d":false},"z07930":{"c":"CHESTER","s":"NJ","d":false},"z07936":{"c":"EAST HANOVER","s":"NJ","d":false},"z07931":{"c":"FAR HILLS","s":"NJ","d":false},"z07932":{"c":"FLORHAM PARK","s":"NJ","d":false},"z07933":{"c":"GILLETTE","s":"NJ","d":false},"z07934":{"c":"GLADSTONE","s":"NJ","d":false},"z07935":{"c":"GREEN VILLAGE","s":"NJ","d":false},"z07938":{"c":"LIBERTY CORNER","s":"NJ","d":false},"z07940":{"c":"MADISON","s":"NJ","d":false},"z07945":{"c":"MENDHAM","s":"NJ","d":false},"z07946":{"c":"MILLINGTON","s":"NJ","d":false},"z07950":{"c":"MORRIS PLAINS","s":"NJ","d":false},"z07960":{"c":"MORRISTOWN","s":"NJ","d":false},"z07961":{"c":"CONVENT STATION","s":"NJ","d":false},"z07962":{"c":"MORRISTOWN","s":"NJ","d":false},"z07963":{"c":"MORRISTOWN","s":"NJ","d":false},"z07970":{"c":"MOUNT FREEDOM","s":"NJ","d":false},"z07974":{"c":"NEW PROVIDENCE","s":"NJ","d":false},"z07976":{"c":"NEW VERNON","s":"NJ","d":false},"z07977":{"c":"PEAPACK","s":"NJ","d":false},"z07978":{"c":"PLUCKEMIN","s":"NJ","d":false},"z07979":{"c":"POTTERSVILLE","s":"NJ","d":false},"z07980":{"c":"STIRLING","s":"NJ","d":false},"z07901":{"c":"SUMMIT","s":"NJ","d":false},"z07902":{"c":"SUMMIT","s":"NJ","d":false},"z07983":{"c":"WHIPPANY","s":"NJ","d":true},"z07900":false,"z07903":false,"z07904":false,"z07905":false,"z07906":false,"z07907":false,"z07908":false,"z07909":false,"z07910":false,"z07911":false,"z07912":false,"z07913":false,"z07914":false,"z07915":false,"z07916":false,"z07917":false,"z07918":false,"z07919":false,"z07923":false,"z07925":false,"z07929":false,"z07937":false,"z07941":false,"z07942":false,"z07943":false,"z07944":false,"z07947":false,"z07948":false,"z07949":false,"z07951":false,"z07952":false,"z07953":false,"z07954":false,"z07955":false,"z07956":false,"z07957":false,"z07958":false,"z07959":false,"z07964":false,"z07965":false,"z07966":false,"z07967":false,"z07968":false,"z07969":false,"z07971":false,"z07972":false,"z07973":false,"z07975":false,"z07982":false,"z07984":false,"z07985":false,"z07986":false,"z07987":false,"z07988":false,"z07989":false,"z07990":false,"z07991":false,"z07992":false,"z07993":false,"z07994":false,"z07995":false,"z07996":false,"z07997":false,"z07998":false}