{"z82410":{"c":"BASIN","s":"WY","d":false},"z82411":{"c":"BURLINGTON","s":"WY","d":false},"z82412":{"c":"BYRON","s":"WY","d":false},"z82414":{"c":"CODY","s":"WY","d":false},"z82420":{"c":"COWLEY","s":"WY","d":false},"z82421":{"c":"DEAVER","s":"WY","d":false},"z82422":{"c":"EMBLEM","s":"WY","d":false},"z82423":{"c":"FRANNIE","s":"WY","d":false},"z82426":{"c":"GREYBULL","s":"WY","d":false},"z82428":{"c":"HYATTVILLE","s":"WY","d":false},"z82431":{"c":"LOVELL","s":"WY","d":false},"z82432":{"c":"MANDERSON","s":"WY","d":false},"z82433":{"c":"MEETEETSE","s":"WY","d":false},"z82434":{"c":"OTTO","s":"WY","d":false},"z82435":{"c":"POWELL","s":"WY","d":false},"z82440":{"c":"RALSTON","s":"WY","d":false},"z82441":{"c":"SHELL","s":"WY","d":false},"z82442":{"c":"TEN SLEEP","s":"WY","d":false},"z82430":{"c":"KIRBY","s":"WY","d":false},"z82443":{"c":"THERMOPOLIS","s":"WY","d":false},"z82450":{"c":"WAPITI","s":"WY","d":false},"z82401":{"c":"WORLAND","s":"WY","d":false},"z82400":false,"z82402":false,"z82403":false,"z82404":false,"z82405":false,"z82406":false,"z82407":false,"z82408":false,"z82409":false,"z82413":false,"z82415":false,"z82416":false,"z82417":false,"z82418":false,"z82419":false,"z82424":false,"z82425":false,"z82427":false,"z82429":false,"z82436":false,"z82437":false,"z82438":false,"z82439":false,"z82444":false,"z82445":false,"z82446":false,"z82447":false,"z82448":false,"z82449":false,"z82451":false,"z82452":false,"z82453":false,"z82454":false,"z82455":false,"z82456":false,"z82457":false,"z82458":false,"z82459":false,"z82460":false,"z82461":false,"z82462":false,"z82463":false,"z82464":false,"z82465":false,"z82466":false,"z82467":false,"z82468":false,"z82469":false,"z82470":false,"z82471":false,"z82472":false,"z82473":false,"z82474":false,"z82475":false,"z82476":false,"z82477":false,"z82478":false,"z82479":false,"z82480":false,"z82481":false,"z82482":false,"z82483":false,"z82484":false,"z82485":false,"z82486":false,"z82487":false,"z82488":false,"z82489":false,"z82490":false,"z82491":false,"z82492":false,"z82493":false,"z82494":false,"z82495":false,"z82496":false,"z82497":false,"z82498":false,"z82499":false}