{"z45710":{"c":"ALBANY","s":"OH","d":false},"z45776":{"c":"SHADE","s":"OH","d":false},"z45711":{"c":"AMESVILLE","s":"OH","d":false},"z45777":{"c":"SHARPSBURG","s":"OH","d":false},"z45701":{"c":"ATHENS","s":"OH","d":false},"z45712":{"c":"BARLOW","s":"OH","d":false},"z45729":{"c":"FLEMING","s":"OH","d":false},"z45713":{"c":"BARTLETT","s":"OH","d":false},"z45714":{"c":"BELPRE","s":"OH","d":false},"z45715":{"c":"BEVERLY","s":"OH","d":false},"z45721":{"c":"COAL RUN","s":"OH","d":false},"z45716":{"c":"BUCHTEL","s":"OH","d":false},"z45719":{"c":"CHAUNCEY","s":"OH","d":false},"z45720":{"c":"CHESTER","s":"OH","d":false},"z45723":{"c":"COOLVILLE","s":"OH","d":false},"z45739":{"c":"HOCKINGPORT","s":"OH","d":false},"z45724":{"c":"CUTLER","s":"OH","d":false},"z45727":{"c":"DEXTER CITY","s":"OH","d":false},"z45732":{"c":"GLOUSTER","s":"OH","d":false},"z45735":{"c":"GUYSVILLE","s":"OH","d":false},"z45740":{"c":"JACKSONVILLE","s":"OH","d":false},"z45741":{"c":"LANGSVILLE","s":"OH","d":false},"z45742":{"c":"LITTLE HOCKING","s":"OH","d":false},"z45743":{"c":"LONG BOTTOM","s":"OH","d":false},"z45744":{"c":"LOWELL","s":"OH","d":false},"z45745":{"c":"LOWER SALEM","s":"OH","d":false},"z45746":{"c":"MACKSBURG","s":"OH","d":false},"z45750":{"c":"MARIETTA","s":"OH","d":false},"z45760":{"c":"MIDDLEPORT","s":"OH","d":false},"z45761":{"c":"MILLFIELD","s":"OH","d":false},"z45717":{"c":"CARBONDALE","s":"OH","d":false},"z45764":{"c":"NELSONVILLE","s":"OH","d":false},"z45766":{"c":"NEW MARSHFIELD","s":"OH","d":false},"z45734":{"c":"GRAYSVILLE","s":"OH","d":false},"z45767":{"c":"NEW MATAMORAS","s":"OH","d":false},"z45789":{"c":"WINGETT RUN","s":"OH","d":false},"z45768":{"c":"NEWPORT","s":"OH","d":false},"z45769":{"c":"POMEROY","s":"OH","d":false},"z45770":{"c":"PORTLAND","s":"OH","d":false},"z45771":{"c":"RACINE","s":"OH","d":false},"z45772":{"c":"REEDSVILLE","s":"OH","d":false},"z45773":{"c":"RENO","s":"OH","d":false},"z45775":{"c":"RUTLAND","s":"OH","d":false},"z45778":{"c":"STEWART","s":"OH","d":false},"z45779":{"c":"SYRACUSE","s":"OH","d":false},"z45780":{"c":"THE PLAINS","s":"OH","d":false},"z45782":{"c":"TRIMBLE","s":"OH","d":false},"z45783":{"c":"TUPPERS PLAINS","s":"OH","d":false},"z45784":{"c":"VINCENT","s":"OH","d":false},"z45786":{"c":"WATERFORD","s":"OH","d":false},"z45787":{"c":"WATERTOWN","s":"OH","d":false},"z45788":{"c":"WHIPPLE","s":"OH","d":false},"z45700":false,"z45702":false,"z45703":false,"z45704":false,"z45705":false,"z45706":false,"z45707":false,"z45708":false,"z45709":false,"z45718":false,"z45722":false,"z45725":false,"z45726":false,"z45728":false,"z45730":false,"z45731":false,"z45733":false,"z45736":false,"z45737":false,"z45738":false,"z45747":false,"z45748":false,"z45749":false,"z45751":false,"z45752":false,"z45753":false,"z45754":false,"z45755":false,"z45756":false,"z45757":false,"z45758":false,"z45759":false,"z45762":false,"z45763":false,"z45765":false,"z45774":false,"z45781":false,"z45785":false,"z45790":false,"z45791":false,"z45792":false,"z45793":false,"z45794":false,"z45795":false,"z45796":false,"z45797":false,"z45798":false,"z45799":false}