{"z35144":{"c":"SILURIA","s":"AL","d":false},"z35111":{"c":"MC CALLA","s":"AL","d":false},"z35112":{"c":"MARGARET","s":"AL","d":false},"z35114":{"c":"MAYLENE","s":"AL","d":false},"z35115":{"c":"MONTEVALLO","s":"AL","d":false},"z35116":{"c":"MORRIS","s":"AL","d":false},"z35117":{"c":"MOUNT OLIVE","s":"AL","d":false},"z35118":{"c":"MULGA","s":"AL","d":false},"z35119":{"c":"NEW CASTLE","s":"AL","d":false},"z35120":{"c":"ODENVILLE","s":"AL","d":false},"z35121":{"c":"ONEONTA","s":"AL","d":false},"z35123":{"c":"PALMERDALE","s":"AL","d":false},"z35124":{"c":"PELHAM","s":"AL","d":false},"z35125":{"c":"PELL CITY","s":"AL","d":false},"z35128":{"c":"PELL CITY","s":"AL","d":false},"z35126":{"c":"PINSON","s":"AL","d":false},"z35127":{"c":"PLEASANT GROVE","s":"AL","d":false},"z35130":{"c":"QUINTON","s":"AL","d":false},"z35131":{"c":"RAGLAND","s":"AL","d":false},"z35133":{"c":"REMLAP","s":"AL","d":false},"z35135":{"c":"RIVERSIDE","s":"AL","d":false},"z35136":{"c":"ROCKFORD","s":"AL","d":false},"z35137":{"c":"SAGINAW","s":"AL","d":false},"z35139":{"c":"SAYRE","s":"AL","d":false},"z35142":{"c":"SHANNON","s":"AL","d":false},"z35143":{"c":"SHELBY","s":"AL","d":false},"z35146":{"c":"SPRINGVILLE","s":"AL","d":false},"z35147":{"c":"STERRETT","s":"AL","d":false},"z35148":{"c":"SUMITON","s":"AL","d":false},"z35149":{"c":"SYCAMORE","s":"AL","d":false},"z35150":{"c":"SYLACAUGA","s":"AL","d":false},"z35151":{"c":"SYLACAUGA","s":"AL","d":false},"z35160":{"c":"TALLADEGA","s":"AL","d":false},"z35161":{"c":"TALLADEGA","s":"AL","d":false},"z35171":{"c":"THORSBY","s":"AL","d":false},"z35172":{"c":"TRAFFORD","s":"AL","d":false},"z35173":{"c":"TRUSSVILLE","s":"AL","d":false},"z35175":{"c":"UNION GROVE","s":"AL","d":false},"z35176":{"c":"VANDIVER","s":"AL","d":false},"z35178":{"c":"VINCENT","s":"AL","d":false},"z35179":{"c":"VINEMONT","s":"AL","d":false},"z35180":{"c":"WARRIOR","s":"AL","d":false},"z35181":{"c":"WATSON","s":"AL","d":false},"z35182":{"c":"WATTSVILLE","s":"AL","d":false},"z35183":{"c":"WEOGUFKA","s":"AL","d":false},"z35184":{"c":"WEST BLOCTON","s":"AL","d":false},"z35185":{"c":"WESTOVER","s":"AL","d":false},"z35186":{"c":"WILSONVILLE","s":"AL","d":false},"z35187":{"c":"WILTON","s":"AL","d":false},"z35188":{"c":"WOODSTOCK","s":"AL","d":false},"z35100":false,"z35101":false,"z35102":false,"z35103":false,"z35104":false,"z35105":false,"z35106":false,"z35107":false,"z35108":false,"z35109":false,"z35110":false,"z35113":false,"z35122":false,"z35129":false,"z35132":false,"z35134":false,"z35138":false,"z35140":false,"z35141":false,"z35145":false,"z35152":false,"z35153":false,"z35154":false,"z35155":false,"z35156":false,"z35157":false,"z35158":false,"z35159":false,"z35162":false,"z35163":false,"z35164":false,"z35165":false,"z35166":false,"z35167":false,"z35168":false,"z35169":false,"z35170":false,"z35174":false,"z35177":false,"z35189":false,"z35190":false,"z35191":false,"z35192":false,"z35193":false,"z35194":false,"z35195":false,"z35196":false,"z35197":false,"z35198":false,"z35199":false}