{"z51230":{"c":"ALVORD","s":"IA","d":false},"z51231":{"c":"ARCHER","s":"IA","d":false},"z51232":{"c":"ASHTON","s":"IA","d":false},"z51234":{"c":"BOYDEN","s":"IA","d":false},"z51235":{"c":"DOON","s":"IA","d":false},"z51237":{"c":"GEORGE","s":"IA","d":false},"z51238":{"c":"HOSPERS","s":"IA","d":false},"z51239":{"c":"HULL","s":"IA","d":false},"z51240":{"c":"INWOOD","s":"IA","d":false},"z51241":{"c":"LARCHWOOD","s":"IA","d":false},"z51242":{"c":"LESTER","s":"IA","d":false},"z51243":{"c":"LITTLE ROCK","s":"IA","d":false},"z51245":{"c":"PRIMGHAR","s":"IA","d":false},"z51246":{"c":"ROCK RAPIDS","s":"IA","d":false},"z51247":{"c":"ROCK VALLEY","s":"IA","d":false},"z51248":{"c":"SANBORN","s":"IA","d":false},"z51201":{"c":"SHELDON","s":"IA","d":false},"z51244":{"c":"MATLOCK","s":"IA","d":false},"z51249":{"c":"SIBLEY","s":"IA","d":false},"z51250":{"c":"SIOUX CENTER","s":"IA","d":false},"z51200":false,"z51202":false,"z51203":false,"z51204":false,"z51205":false,"z51206":false,"z51207":false,"z51208":false,"z51209":false,"z51210":false,"z51211":false,"z51212":false,"z51213":false,"z51214":false,"z51215":false,"z51216":false,"z51217":false,"z51218":false,"z51219":false,"z51220":false,"z51221":false,"z51222":false,"z51223":false,"z51224":false,"z51225":false,"z51226":false,"z51227":false,"z51228":false,"z51229":false,"z51233":false,"z51236":false,"z51251":false,"z51252":false,"z51253":false,"z51254":false,"z51255":false,"z51256":false,"z51257":false,"z51258":false,"z51259":false,"z51260":false,"z51261":false,"z51262":false,"z51263":false,"z51264":false,"z51265":false,"z51266":false,"z51267":false,"z51268":false,"z51269":false,"z51270":false,"z51271":false,"z51272":false,"z51273":false,"z51274":false,"z51275":false,"z51276":false,"z51277":false,"z51278":false,"z51279":false,"z51280":false,"z51281":false,"z51282":false,"z51283":false,"z51284":false,"z51285":false,"z51286":false,"z51287":false,"z51288":false,"z51289":false,"z51290":false,"z51291":false,"z51292":false,"z51293":false,"z51294":false,"z51295":false,"z51296":false,"z51297":false,"z51298":false,"z51299":false}