{"z46401":{"c":"GARY","s":"IN","d":false},"z46402":{"c":"GARY","s":"IN","d":false},"z46403":{"c":"GARY","s":"IN","d":false},"z46404":{"c":"GARY","s":"IN","d":false},"z46405":{"c":"LAKE STATION","s":"IN","d":false},"z46406":{"c":"GARY","s":"IN","d":false},"z46407":{"c":"GARY","s":"IN","d":false},"z46408":{"c":"GARY","s":"IN","d":false},"z46409":{"c":"GARY","s":"IN","d":false},"z46410":{"c":"MERRILLVILLE","s":"IN","d":false},"z46411":{"c":"MERRILLVILLE","s":"IN","d":false},"z46400":false,"z46412":false,"z46413":false,"z46414":false,"z46415":false,"z46416":false,"z46417":false,"z46418":false,"z46419":false,"z46420":false,"z46421":false,"z46422":false,"z46423":false,"z46424":false,"z46425":false,"z46426":false,"z46427":false,"z46428":false,"z46429":false,"z46430":false,"z46431":false,"z46432":false,"z46433":false,"z46434":false,"z46435":false,"z46436":false,"z46437":false,"z46438":false,"z46439":false,"z46440":false,"z46441":false,"z46442":false,"z46443":false,"z46444":false,"z46445":false,"z46446":false,"z46447":false,"z46448":false,"z46449":false,"z46450":false,"z46451":false,"z46452":false,"z46453":false,"z46454":false,"z46455":false,"z46456":false,"z46457":false,"z46458":false,"z46459":false,"z46460":false,"z46461":false,"z46462":false,"z46463":false,"z46464":false,"z46465":false,"z46466":false,"z46467":false,"z46468":false,"z46469":false,"z46470":false,"z46471":false,"z46472":false,"z46473":false,"z46474":false,"z46475":false,"z46476":false,"z46477":false,"z46478":false,"z46479":false,"z46480":false,"z46481":false,"z46482":false,"z46483":false,"z46484":false,"z46485":false,"z46486":false,"z46487":false,"z46488":false,"z46489":false,"z46490":false,"z46491":false,"z46492":false,"z46493":false,"z46494":false,"z46495":false,"z46496":false,"z46497":false,"z46498":false,"z46499":false}