{"z79101":{"c":"AMARILLO","s":"TX","d":false},"z79102":{"c":"AMARILLO","s":"TX","d":false},"z79103":{"c":"AMARILLO","s":"TX","d":false},"z79104":{"c":"AMARILLO","s":"TX","d":false},"z79105":{"c":"AMARILLO","s":"TX","d":false},"z79106":{"c":"AMARILLO","s":"TX","d":false},"z79107":{"c":"AMARILLO","s":"TX","d":false},"z79108":{"c":"AMARILLO","s":"TX","d":false},"z79109":{"c":"AMARILLO","s":"TX","d":false},"z79110":{"c":"AMARILLO","s":"TX","d":false},"z79111":{"c":"AMARILLO","s":"TX","d":false},"z79114":{"c":"AMARILLO","s":"TX","d":false},"z79116":{"c":"AMARILLO","s":"TX","d":false},"z79117":{"c":"AMARILLO","s":"TX","d":false},"z79118":{"c":"AMARILLO","s":"TX","d":false},"z79119":{"c":"AMARILLO","s":"TX","d":false},"z79120":{"c":"AMARILLO","s":"TX","d":false},"z79121":{"c":"AMARILLO","s":"TX","d":false},"z79124":{"c":"AMARILLO","s":"TX","d":false},"z79159":{"c":"AMARILLO","s":"TX","d":false},"z79166":{"c":"AMARILLO","s":"TX","d":false},"z79168":{"c":"AMARILLO","s":"TX","d":false},"z79172":{"c":"AMARILLO","s":"TX","d":false},"z79174":{"c":"AMARILLO","s":"TX","d":false},"z79178":{"c":"AMARILLO","s":"TX","d":false},"z79185":{"c":"AMARILLO","s":"TX","d":false},"z79189":{"c":"AMARILLO","s":"TX","d":false},"z79187":{"c":"AMARILLO","s":"TX","d":true},"z79100":false,"z79112":false,"z79113":false,"z79115":false,"z79122":false,"z79123":false,"z79125":false,"z79126":false,"z79127":false,"z79128":false,"z79129":false,"z79130":false,"z79131":false,"z79132":false,"z79133":false,"z79134":false,"z79135":false,"z79136":false,"z79137":false,"z79138":false,"z79139":false,"z79140":false,"z79141":false,"z79142":false,"z79143":false,"z79144":false,"z79145":false,"z79146":false,"z79147":false,"z79148":false,"z79149":false,"z79150":false,"z79151":false,"z79152":false,"z79153":false,"z79154":false,"z79155":false,"z79156":false,"z79157":false,"z79158":false,"z79160":false,"z79161":false,"z79162":false,"z79163":false,"z79164":false,"z79165":false,"z79167":false,"z79169":false,"z79170":false,"z79171":false,"z79173":false,"z79175":false,"z79176":false,"z79177":false,"z79179":false,"z79180":false,"z79181":false,"z79182":false,"z79183":false,"z79184":false,"z79186":false,"z79188":false,"z79190":false,"z79191":false,"z79192":false,"z79193":false,"z79194":false,"z79195":false,"z79196":false,"z79197":false,"z79198":false,"z79199":false}